<?xml version="1.0" encoding="utf-8"?>
<VisualState xmlns:xsi="http://www.w3.org/2001/XMLSchema-instance" xmlns:xsd="http://www.w3.org/2001/XMLSchema" ShowCheckBoxes="false">
  <TopNode>[0-1000]E:\WORK\WORK\ITRANSITION\Training\Itransition.Training.Data\Data.nunit</TopNode>
  <SelectedNode>[0-1003]Itransition.Training.Data.TagTest.Delete</SelectedNode>
  <ExcludeCategories>false</ExcludeCategories>
  <Nodes>
    <Node UniqueName="[0-1000]E:\WORK\WORK\ITRANSITION\Training\Itransition.Training.Data\Data.nunit" Expanded="true">
      <Nodes>
        <Node UniqueName="[0-1011]E:\WORK\WORK\ITRANSITION\Training\Itransition.Training.Data\bin\Debug\Itransition.Training.Data.dll" Expanded="true">
          <Nodes>
            <Node UniqueName="[0-1012]Itransition" Expanded="true">
              <Nodes>
                <Node UniqueName="[0-1013]Itransition.Training" Expanded="true">
                  <Nodes>
                    <Node UniqueName="[0-1014]Itransition.Training.Data" Expanded="true">
                      <Nodes>
                        <Node UniqueName="[0-1006]Itransition.Training.Data.ArticleTest" Expanded="true">
                          <Nodes>
                            <Node UniqueName="[0-1007]Itransition.Training.Data.ArticleTest.Add" />
                            <Node UniqueName="[0-1008]Itransition.Training.Data.ArticleTest.Delete" />
                            <Node UniqueName="[0-1010]Itransition.Training.Data.ArticleTest.Get" />
                            <Node UniqueName="[0-1009]Itransition.Training.Data.ArticleTest.GetAll" />
                          </Nodes>
                        </Node>
                        <Node UniqueName="[0-1001]Itransition.Training.Data.TagTest" Expanded="true">
                          <Nodes>
                            <Node UniqueName="[0-1002]Itransition.Training.Data.TagTest.Add" />
                            <Node UniqueName="[0-1005]Itransition.Training.Data.TagTest.Contains" />
                            <Node UniqueName="[0-1003]Itransition.Training.Data.TagTest.Delete" />
                            <Node UniqueName="[0-1004]Itransition.Training.Data.TagTest.GetAll" />
                          </Nodes>
                        </Node>
                      </Nodes>
                    </Node>
                  </Nodes>
                </Node>
              </Nodes>
            </Node>
          </Nodes>
        </Node>
        <Node UniqueName="[0-1025]E:\WORK\WORK\ITRANSITION\Training\Itransition.Training.Data\bin\Debug\Itransition.Training.Data.dll">
          <Nodes>
            <Node UniqueName="[0-1026]Itransition">
              <Nodes>
                <Node UniqueName="[0-1027]Itransition.Training">
                  <Nodes>
                    <Node UniqueName="[0-1028]Itransition.Training.Data">
                      <Nodes>
                        <Node UniqueName="[0-1020]Itransition.Training.Data.ArticleTest">
                          <Nodes>
                            <Node UniqueName="[0-1021]Itransition.Training.Data.ArticleTest.Add" />
                            <Node UniqueName="[0-1022]Itransition.Training.Data.ArticleTest.Delete" />
                            <Node UniqueName="[0-1024]Itransition.Training.Data.ArticleTest.Get" />
                            <Node UniqueName="[0-1023]Itransition.Training.Data.ArticleTest.GetAll" />
                          </Nodes>
                        </Node>
                        <Node UniqueName="[0-1015]Itransition.Training.Data.TagTest">
                          <Nodes>
                            <Node UniqueName="[0-1016]Itransition.Training.Data.TagTest.Add" />
                            <Node UniqueName="[0-1019]Itransition.Training.Data.TagTest.Contains" />
                            <Node UniqueName="[0-1017]Itransition.Training.Data.TagTest.Delete" />
                            <Node UniqueName="[0-1018]Itransition.Training.Data.TagTest.GetAll" />
                          </Nodes>
                        </Node>
                      </Nodes>
                    </Node>
                  </Nodes>
                </Node>
              </Nodes>
            </Node>
          </Nodes>
        </Node>
      </Nodes>
    </Node>
  </Nodes>
</VisualState>